tomegathericon/utils/exceptions/__init__.py
tomegathericon/utils/exceptions/base.py
tomegathericon/utils/exceptions/py.typed
tomegathericon_utils_exceptions-0.0.2.dist-info/METADATA
tomegathericon_utils_exceptions-0.0.2.dist-info/WHEEL
tomegathericon_utils_exceptions-0.0.2.dist-info/RECORD
