Metadata-Version: 2.3
Name: tomegathericon-utils-exceptions
Version: 0.0.2
Summary: Various High Level Exceptions
License: Software License Agreement
Author: Abhishek Kapoor
Author-email: kapoor.abhishek@outlook.com
Requires-Python: >=3.12,<4.0
Classifier: License :: Other/Proprietary License
Classifier: Programming Language :: Python :: 3
Classifier: Programming Language :: Python :: 3.12
Classifier: Programming Language :: Python :: 3.13
